aiconfig_extension_llama_guard/LLamaGuard.py
aiconfig_extension_llama_guard/__init__.py
aiconfig_extension_llama_guard-0.0.3.dist-info/LICENSE
aiconfig_extension_llama_guard-0.0.3.dist-info/METADATA
aiconfig_extension_llama_guard-0.0.3.dist-info/WHEEL
aiconfig_extension_llama_guard-0.0.3.dist-info/top_level.txt
aiconfig_extension_llama_guard-0.0.3.dist-info/RECORD
