Metadata-Version: 2.1
Name: aiconfig_extension_llama_guard
Version: 0.0.3
Summary: An extension for using LLama Guard with aiconfig
Author: LastMile AI
Author-email: Ankush Pala <ankush@lastmileai.dev>, Rossdan Craig <rossdan@lastmileai.dev>
Project-URL: Homepage, https://github.com/lastmile-ai/aiconfig/
Project-URL: Issues, https://github.com/lastmile-ai/aiconfig/issues
Classifier: Programming Language :: Python :: 3
Classifier: License :: OSI Approved :: MIT License
Classifier: Operating System :: OS Independent
Requires-Python: >=3.10
License-File: LICENSE
Requires-Dist: accelerate ==0.25.0
Requires-Dist: transformers ==4.35.2
Requires-Dist: torch ==2.1.0
Requires-Dist: asyncio
Requires-Dist: python-aiconfig
